drf_toolkit/__init__.py
drf_toolkit/decorators.py
drf_toolkit/drf_utils.py
drf_toolkit/errors.py
drf_toolkit/json_api_views.py
drf_toolkit/json_parser.py
examples/__init__.py
examples/views.py
tests/__init__.py
tests/common_tests.py
drf_toolkit-0.0.21.dist-info/LICENSE
drf_toolkit-0.0.21.dist-info/METADATA
drf_toolkit-0.0.21.dist-info/WHEEL
drf_toolkit-0.0.21.dist-info/top_level.txt
drf_toolkit-0.0.21.dist-info/RECORD
