Metadata-Version: 2.1
Name: drf-toolkit
Version: 0.0.21
Summary: Django rest framework toolkit
Home-page: https://github.com/agorinenko/drf-toolkit
Author: Gorinenko Anton
Author-email: anton.gorinenko@gmail.com
License: UNKNOWN
Keywords: python,drf,django rest framework,toolkit,utils
Platform: UNKNOWN
Classifier: Programming Language :: Python :: 3.7
Classifier: Programming Language :: Python :: 3.8
Classifier: License :: OSI Approved :: MIT License
Classifier: Operating System :: OS Independent
Classifier: Environment :: Web Environment
Classifier: Framework :: Django
Classifier: Framework :: Django :: 2.2
Requires-Python: >=3.7
Requires-Dist: try-parse
Requires-Dist: power-dict (>=0.0.11)
Requires-Dist: djangorestframework
Requires-Dist: django (>=2.2)
